{
   "jawOpenness" : 23.35005760192871,
   "leftEyeOpenness" : 2.575311422348022,
   "leftEyebrowHeight" : 7.294007301330566,
   "mouthHeight" : 3.499605655670166,
   "mouthWidth" : 16.72616577148438,
   "nostrilFlare" : 6.893741607666016,
   "rightEyeOpenness" : 2.523908615112305,
   "rightEyebrowHeight" : 7.334220886230469,
   "vertices" : [
      [ 0, 0 ],
      [ 0, 0 ],
      [ 0, 0 ],
      [ 0, 0 ],
      [ 0, 0 ],
      [ 0, 0 ],
      [ 0, 0 ],
      [ 0, 0 ],
      [ 0, 0 ],
      [ 0, 0 ],
      [ 0, 0 ],
      [ 0, 0 ],
      [ 0, 0 ],
      [ 0, 0 ],
      [ 0, 0 ],
      [ 0, 0 ],
      [ 0, 0 ],
      [ 0, 0 ],
      [ 0, 0 ],
      [ 0, 0 ],
      [ 0, 0 ],
      [ 0, 0 ],
      [ 0, 0 ],
      [ 0, 0 ],
      [ 0, 0 ],
      [ 0, 0 ],
      [ 0, 0 ],
      [ 0, 0 ],
      [ 0, 0 ],
      [ 0, 0 ],
      [ 0, 0 ],
      [ 0, 0 ],
      [ 0, 0 ],
      [ 0, 0 ],
      [ 0, 0 ],
      [ 0, 0 ],
      [ 0, 0 ],
      [ 0, 0 ],
      [ 0, 0 ],
      [ 0, 0 ],
      [ 0, 0 ],
      [ 0, 0 ],
      [ 0, 0 ],
      [ 0, 0 ],
      [ 0, 0 ],
      [ 0, 0 ],
      [ 0, 0 ],
      [ 0, 0 ],
      [ 0, 0 ],
      [ 0, 0 ],
      [ 0, 0 ],
      [ 0, 0 ],
      [ 0, 0 ],
      [ 0, 0 ],
      [ 0, 0 ],
      [ 0, 0 ],
      [ 0, 0 ],
      [ 0, 0 ],
      [ 0, 0 ],
      [ 0, 0 ],
      [ 0, 0 ],
      [ 0, 0 ],
      [ 0, 0 ],
      [ 0, 0 ],
      [ 0, 0 ],
      [ 0, 0 ]
   ]
}

