{
   "jawOpenness" : 23.71243095397949,
   "leftEyeOpenness" : 2.939200162887573,
   "leftEyebrowHeight" : 7.389717578887939,
   "mouthHeight" : 3.895851373672485,
   "mouthWidth" : 17.00884628295898,
   "nostrilFlare" : 6.411060333251953,
   "rightEyeOpenness" : 2.897300004959106,
   "rightEyebrowHeight" : 7.4501051902771,
   "vertices" : [
      [ 0, 0 ],
      [ 0, 0 ],
      [ 0, 0 ],
      [ 0, 0 ],
      [ 0, 0 ],
      [ 0, 0 ],
      [ 0, 0 ],
      [ 0, 0 ],
      [ 0, 0 ],
      [ 0, 0 ],
      [ 0, 0 ],
      [ 0, 0 ],
      [ 0, 0 ],
      [ 0, 0 ],
      [ 0, 0 ],
      [ 0, 0 ],
      [ 0, 0 ],
      [ 0, 0 ],
      [ 0, 0 ],
      [ 0, 0 ],
      [ 0, 0 ],
      [ 0, 0 ],
      [ 0, 0 ],
      [ 0, 0 ],
      [ 0, 0 ],
      [ 0, 0 ],
      [ 0, 0 ],
      [ 0, 0 ],
      [ 0, 0 ],
      [ 0, 0 ],
      [ 0, 0 ],
      [ 0, 0 ],
      [ 0, 0 ],
      [ 0, 0 ],
      [ 0, 0 ],
      [ 0, 0 ],
      [ 0, 0 ],
      [ 0, 0 ],
      [ 0, 0 ],
      [ 0, 0 ],
      [ 0, 0 ],
      [ 0, 0 ],
      [ 0, 0 ],
      [ 0, 0 ],
      [ 0, 0 ],
      [ 0, 0 ],
      [ 0, 0 ],
      [ 0, 0 ],
      [ 0, 0 ],
      [ 0, 0 ],
      [ 0, 0 ],
      [ 0, 0 ],
      [ 0, 0 ],
      [ 0, 0 ],
      [ 0, 0 ],
      [ 0, 0 ],
      [ 0, 0 ],
      [ 0, 0 ],
      [ 0, 0 ],
      [ 0, 0 ],
      [ 0, 0 ],
      [ 0, 0 ],
      [ 0, 0 ],
      [ 0, 0 ],
      [ 0, 0 ],
      [ 0, 0 ]
   ]
}

